YMContent/__init__.py
YMContent/constants.py
YMContent/exceptions.py
YMContent/objects.py
YMContent/response.py
YMContent-0.2.6.dist-info/DESCRIPTION.rst
YMContent-0.2.6.dist-info/METADATA
YMContent-0.2.6.dist-info/RECORD
YMContent-0.2.6.dist-info/WHEEL
YMContent-0.2.6.dist-info/metadata.json
YMContent-0.2.6.dist-info/top_level.txt
