Metadata-Version: 2.0
Name: YMContent
Version: 0.2.6
Summary: Yandex.Market Content API SDK
Home-page: https://github.com/yegorov-p/YMContent
Author: Pavel Yegorov
Author-email: yegorov.p@gmail.com
License: UNKNOWN
Keywords: yandex market
Platform: UNKNOWN
Classifier: Development Status :: 4 - Beta
Classifier: Programming Language :: Python
Classifier: Topic :: Software Development :: Libraries
Requires-Dist: requests
